watermark/__init__.py
watermark/magic.py
watermark/version.py
watermark/watermark.py
watermark-2.6.0.dist-info/licenses/LICENSE
watermark-2.6.0.dist-info/METADATA
watermark-2.6.0.dist-info/WHEEL
watermark-2.6.0.dist-info/top_level.txt
watermark-2.6.0.dist-info/RECORD
